[
  {
    "ciclo": "3",
    "escuela": "FP",
    "codigo_de_asignatura": "C2S20432",
    "asignatura": "SEMINARIO DE FINANZAS INTERNACIONALES",
    "seccion": 1,
    "aula": "N/A",
    "identificacion": "09929287",
    "apellido_paterno": "ELGEGREN",
    "apellido_materno": "APUELA",
    "nombres": "JOSÉ ANTONIO",
    "dia_de_la_semana": "LUNES",
    "hora_de_inicio": "19:00:00",
    "hora_de_finalizacion": "22:00:00",
    "rectificacion": false,
    "codigo_de_asignatura_de_referencia": "undefined",
    "seccion_de_referencia": "undefined",
    "aula_de_referencia": null
  },
  {
    "ciclo": "4",
    "escuela": "FP",
    "codigo_de_asignatura": "C2S20441",
    "asignatura": "SISTEMA NACIONAL DE PROGRAMACIÓN MULTIANUAL Y GESTIÓN DE INVERSIONES. LAS ASOCIACIONES PÚBLICAS PRIVADAS - APP Y OBRAS POR IMPUESTOS",
    "seccion": 1,
    "aula": "N/A",
    "identificacion": "06053691",
    "apellido_paterno": "TORRES",
    "apellido_materno": "TELLO",
    "nombres": "SAMUEL",
    "dia_de_la_semana": "LUNES",
    "hora_de_inicio": "19:00:00",
    "hora_de_finalizacion": "22:00:00",
    "rectificacion": false,
    "codigo_de_asignatura_de_referencia": "undefined",
    "seccion_de_referencia": "undefined",
    "aula_de_referencia": null
  },
  {
    "ciclo": "3",
    "escuela": "FP",
    "codigo_de_asignatura": "C2S20431",
    "asignatura": "GESTIÓN POR PROCESOS EN LA ADMINISTRACIÓN PÚBLICA",
    "seccion": 1,
    "aula": "N/A",
    "identificacion": "32987990",
    "apellido_paterno": "CASTILLO",
    "apellido_materno": "TORREALVA",
    "nombres": "LUIS JUAN",
    "dia_de_la_semana": "LUNES",
    "hora_de_inicio": "19:00:00",
    "hora_de_finalizacion": "22:00:00",
    "rectificacion": false,
    "codigo_de_asignatura_de_referencia": "undefined",
    "seccion_de_referencia": "undefined",
    "aula_de_referencia": null
  },
  {
    "ciclo": "3",
    "escuela": "FP",
    "codigo_de_asignatura": "C2S20434",
    "asignatura": "TALLER DE TESIS II",
    "seccion": 1,
    "aula": "N/A",
    "identificacion": "08204035",
    "apellido_paterno": "UGARTE",
    "apellido_materno": "CASAFRANCA",
    "nombres": "WALTER DAVID",
    "dia_de_la_semana": "MIÉRCOLES",
    "hora_de_inicio": "19:00:00",
    "hora_de_finalizacion": "22:00:00",
    "rectificacion": false,
    "codigo_de_asignatura_de_referencia": "undefined",
    "seccion_de_referencia": "undefined",
    "aula_de_referencia": null
  },
  {
    "ciclo": "3",
    "escuela": "FP",
    "codigo_de_asignatura": "C2S20433",
    "asignatura": "SEMINARIO DE INTEGRIDAD Y ÉTICA EN LA GESTIÓN PÚBLICA",
    "seccion": 1,
    "aula": "N/A",
    "identificacion": "08531847",
    "apellido_paterno": "BACA",
    "apellido_materno": "MORANTE",
    "nombres": "YANETTE ARMIDA",
    "dia_de_la_semana": "VIERNES",
    "hora_de_inicio": "19:00:00",
    "hora_de_finalizacion": "22:00:00",
    "rectificacion": false,
    "codigo_de_asignatura_de_referencia": "undefined",
    "seccion_de_referencia": "undefined",
    "aula_de_referencia": null
  },
  {
    "ciclo": "5",
    "escuela": "DPFST",
    "codigo_de_asignatura": "C2010251",
    "asignatura": "DIRECCIÓN DE TESIS I",
    "seccion": 1,
    "aula": "N/A",
    "identificacion": "43564026",
    "apellido_paterno": "VIVANCO",
    "apellido_materno": "AQUINO",
    "nombres": "IVAN DAZIR BERLEINE",
    "dia_de_la_semana": "SÁBADO",
    "hora_de_inicio": "15:00:00",
    "hora_de_finalizacion": "18:45:00",
    "rectificacion": true,
    "codigo_de_asignatura_de_referencia": "C2010152",
    "seccion_de_referencia": "1",
    "aula_de_referencia": null
  },
  {
    "ciclo": "3",
    "escuela": "FP",
    "codigo_de_asignatura": "C2S20403",
    "asignatura": "PEDAGOGÍA UNIVERSITARIA",
    "seccion": 1,
    "aula": "N/A",
    "identificacion": "07260137",
    "apellido_paterno": "LOPEZ",
    "apellido_materno": "MORALES",
    "nombres": "TOMASA FELICIDAD",
    "dia_de_la_semana": "VIERNES",
    "hora_de_inicio": "19:00:00",
    "hora_de_finalizacion": "22:00:00",
    "rectificacion": false,
    "codigo_de_asignatura_de_referencia": "undefined",
    "seccion_de_referencia": "undefined",
    "aula_de_referencia": null
  },
  {
    "ciclo": "4",
    "escuela": "FP",
    "codigo_de_asignatura": "C2S20443",
    "asignatura": "SEMINARIO DE GOBIERNO DIGITAL",
    "seccion": 1,
    "aula": "N/A",
    "identificacion": "08687564",
    "apellido_paterno": "GUEVARA",
    "apellido_materno": "MONTESINOS",
    "nombres": "WERNHER OMAR",
    "dia_de_la_semana": "VIERNES",
    "hora_de_inicio": "19:00:00",
    "hora_de_finalizacion": "22:00:00",
    "rectificacion": false,
    "codigo_de_asignatura_de_referencia": "undefined",
    "seccion_de_referencia": "undefined",
    "aula_de_referencia": null
  },
  {
    "ciclo": "4",
    "escuela": "FP",
    "codigo_de_asignatura": "C2S20444",
    "asignatura": "TALLER DE TESIS III",
    "seccion": 1,
    "aula": "N/A",
    "identificacion": "16744141",
    "apellido_paterno": "FIESTAS",
    "apellido_materno": "FLORES",
    "nombres": "ROBERTO CARLOS",
    "dia_de_la_semana": "MIÉRCOLES",
    "hora_de_inicio": "19:00:00",
    "hora_de_finalizacion": "22:00:00",
    "rectificacion": false,
    "codigo_de_asignatura_de_referencia": "undefined",
    "seccion_de_referencia": "undefined",
    "aula_de_referencia": null
  },
  {
    "ciclo": "5",
    "escuela": "DCCE",
    "codigo_de_asignatura": "C2010152",
    "asignatura": "DIRECCIÓN DE TESIS I",
    "seccion": 1,
    "aula": "N/A",
    "identificacion": "43564026",
    "apellido_paterno": "VIVANCO",
    "apellido_materno": "AQUINO",
    "nombres": "IVAN DAZIR BERLEINE",
    "dia_de_la_semana": "SÁBADO",
    "hora_de_inicio": "15:00:00",
    "hora_de_finalizacion": "18:45:00",
    "rectificacion": false,
    "codigo_de_asignatura_de_referencia": "undefined",
    "seccion_de_referencia": "undefined",
    "aula_de_referencia": null
  },
  {
    "ciclo": "3",
    "escuela": "B Y F",
    "codigo_de_asignatura": "C3S20132",
    "asignatura": "TALLER DE TESIS II",
    "seccion": 2,
    "aula": "N/A",
    "identificacion": "08592177",
    "apellido_paterno": "MEDIANERO",
    "apellido_materno": "BURGA",
    "nombres": "ELPIDIO DAVID",
    "dia_de_la_semana": "MIÉRCOLES",
    "hora_de_inicio": "19:00:00",
    "hora_de_finalizacion": "22:00:00",
    "rectificacion": true,
    "codigo_de_asignatura_de_referencia": "C3P20132",
    "seccion_de_referencia": "2",
    "aula_de_referencia": null
  },
  {
    "ciclo": "4",
    "escuela": "FP",
    "codigo_de_asignatura": "C2S20442",
    "asignatura": "LOS SISTEMAS ADMINISTRATIVOS Y FUNCIONALES",
    "seccion": 1,
    "aula": "N/A",
    "identificacion": "09309526",
    "apellido_paterno": "MUÑANTE",
    "apellido_materno": "VALENZUELA",
    "nombres": "FORTUNATO LEOPOLDO",
    "dia_de_la_semana": "VIERNES",
    "hora_de_inicio": "19:00:00",
    "hora_de_finalizacion": "22:00:00",
    "rectificacion": false,
    "codigo_de_asignatura_de_referencia": "undefined",
    "seccion_de_referencia": "undefined",
    "aula_de_referencia": null
  }
]