[{"MAESTRIA":"AGE","CODIGO":"C3S2A211","ASIGNATURA":"NIA (ISA)","HR":2,"CR":2,"Ciclo":1,"DOCENTE":"Flores Konja, Adrián Alejandro","MODULO":2,"horarios":{"SÁBADO":"11:00-14:00"},"seccion":1},{"MAESTRIA":"AGE","CODIGO":"C3S2A212","ASIGNATURA":"HABILIDADES GERENCIALES","HR":2,"CR":3,"Ciclo":1,"DOCENTE":"Palomino Silva, Julio Andres","MODULO":1,"horarios":{"SÁBADO":"15:00-18:00"},"seccion":1},{"MAESTRIA":"AGE","CODIGO":"C3S2A213","ASIGNATURA":"DOCTRINA Y FILOSOFIA CONTABLE","HR":2,"CR":3,"Ciclo":1,"DOCENTE":"Masuda Toyofuku, Victor Ricardo","MODULO":1,"horarios":{"SÁBADO":"11:00-14:00"},"seccion":1},{"MAESTRIA":"AGE","CODIGO":"C3S2A222","ASIGNATURA":"TALLER DE TESIS  I","HR":4,"CR":9,"Ciclo":2,"DOCENTE":"Caballero Montañez, Raúl Walter","MODULO":1,"horarios":{"SÁBADO":"08:00-11:00"},"seccion":1},{"MAESTRIA":"AGE","CODIGO":"C3S2A221","ASIGNATURA":"GOBIERNO CORPORATIVO","HR":2,"CR":3,"Ciclo":2,"DOCENTE":"Elgegren Apuela, José Antonio","MODULO":1,"horarios":{"SÁBADO":"15:00-18:00"},"seccion":1},{"MAESTRIA":"AGE","CODIGO":"C3S2A223","ASIGNATURA":"TALLER DE INVESTIGACION DE LA GESTION EMPRESARIAL Y PROCESOS ADMINISTRATIVOS","HR":2,"CR":2,"Ciclo":2,"DOCENTE":"Ortiz Burga, Arturo Guillermo","MODULO":1,"horarios":{"SÁBADO":"11:00-14:00"},"seccion":1},{"MAESTRIA":"AGE","CODIGO":"C3S2A224","ASIGNATURA":"TALLER DE ANALISIS DE RIESGOS Y PROCESOS","HR":2,"CR":3,"Ciclo":2,"DOCENTE":"Villacorta Cavero, Armando Manuel","MODULO":2,"horarios":{"SÁBADO":"15:00-18:00"},"seccion":1},{"MAESTRIA":"AGE","CODIGO":"C3S2A232","ASIGNATURA":"TALLER DE TESIS II","HR":4,"CR":10,"Ciclo":3,"DOCENTE":"Garay Argandoña, Rafael Antonio","MODULO":1,"horarios":{"SÁBADO":"08:00-11:00"},"seccion":1},{"MAESTRIA":"AGE","CODIGO":"C3S2A231","ASIGNATURA":"AUDITORIA DE TECNOLOGIAS DE LA INFORMACION","HR":2,"CR":2,"Ciclo":3,"DOCENTE":"Rojas Medina, Julio César","MODULO":2,"horarios":{"SÁBADO":"15:00-18:00"},"seccion":1},{"MAESTRIA":"AGE","CODIGO":"C3S2A233","ASIGNATURA":"ESTADISTICA APLICADA A LA INVESTIGACION","HR":2,"CR":2,"Ciclo":3,"DOCENTE":"Cerna Maguiña, Hector Felix","MODULO":1,"horarios":{"SÁBADO":"15:00-18:00"},"seccion":1},{"MAESTRIA":"AGE","CODIGO":"C3S2A234","ASIGNATURA":"SEMINARIO DE AUDITORIA FINANCIERA (DICTAMENES DE AUDITORIA)","HR":2,"CR":3,"Ciclo":3,"DOCENTE":"Urbano Ventocilla, Cesar Maximiliano","MODULO":2,"horarios":{"SÁBADO":"11:00-14:00"},"seccion":1},{"MAESTRIA":"AGE","CODIGO":"C3S2A2A2","ASIGNATURA":"(e) TALLER DE CONTROL INTERNO","HR":2,"CR":2,"Ciclo":3,"DOCENTE":"Granda Carazas, Segundo Eloy","MODULO":1,"horarios":{"SÁBADO":"11:00-14:00"},"seccion":1},{"MAESTRIA":"AGE","CODIGO":"C3P21242","ASIGNATURA":"TALLER DE TESIS  III","HR":4,"CR":10,"Ciclo":4,"DOCENTE":"Rozas Flores, Alan Errol","MODULO":1,"horarios":{"SÁBADO":"08:00-11:00"},"seccion":1},{"MAESTRIA":"AGE","CODIGO":"C3P21241","ASIGNATURA":"AUDITORIA FORENSE","HR":2,"CR":3,"Ciclo":4,"DOCENTE":"Durand Saavedra, Demetrio Pedro","MODULO":1,"horarios":{"SÁBADO":"15:00-18:00"},"seccion":1},{"MAESTRIA":"AGE","CODIGO":"C3P21243","ASIGNATURA":"TALLER DE NEGOCIACIÓN Y LIDERAZGO","HR":2,"CR":2,"Ciclo":4,"DOCENTE":"Olortegui Muro, Camilo Adrian","MODULO":2,"horarios":{"SÁBADO":"11:00-14:00"},"seccion":1},{"MAESTRIA":"AGE","CODIGO":"C3P21244","ASIGNATURA":"SEMINARIO DE ÉTICA EN LOS NEGOCIOS","HR":2,"CR":2,"Ciclo":4,"DOCENTE":"Salazar Frisancho, Angel Roberto","MODULO":1,"horarios":{"SÁBADO":"11:00-14:00"},"seccion":1},{"MAESTRIA":"AGCG","CODIGO":"C3S22214","ASIGNATURA":"METODOLOGÍA Y DISEÑO DE LA INVESTIGACION","HR":4,"CR":9,"Ciclo":1,"DOCENTE":"Gomez Jacinto, Luis Gerardo","MODULO":1,"horarios":{"SÁBADO":"08:00-11:00"},"seccion":1},{"MAESTRIA":"AGCG","CODIGO":"C3S22211","ASIGNATURA":"CONTABILIDAD Y PRESUPUESTO GUBERNAMENTAL","HR":2,"CR":3,"Ciclo":1,"DOCENTE":"Laban Elera, Hugo Neptali","MODULO":1,"horarios":{"SÁBADO":"15:00-18:00"},"seccion":1},{"MAESTRIA":"AGCG","CODIGO":"C3S22212","ASIGNATURA":"SISTEMA DE GESTION PUBLICA","HR":2,"CR":2,"Ciclo":1,"DOCENTE":"Castillo Torrealva, Luis Juan","MODULO":2,"horarios":{"SÁBADO":"11:00-14:00"},"seccion":1},{"MAESTRIA":"AGCG","CODIGO":"C3S22213","ASIGNATURA":"CONTROL INTERNO Y GESTION DE RIESGOS EN EL ESTADO","HR":2,"CR":2,"Ciclo":1,"DOCENTE":"Mogrovejo Espinoza, Martín Edmundo","MODULO":1,"horarios":{"SÁBADO":"11:00-14:00"},"seccion":1},{"MAESTRIA":"AGCG","CODIGO":"C3S22222","ASIGNATURA":"TALLER DE TESIS  I","HR":4,"CR":9,"Ciclo":2,"DOCENTE":"Holgado Dorado, Kilder","MODULO":1,"horarios":{"SÁBADO":"08:00-11:00"},"seccion":1},{"MAESTRIA":"AGCG","CODIGO":"C3S22221","ASIGNATURA":"AUDITORIA PRESUPUESTAL","HR":2,"CR":2,"Ciclo":2,"DOCENTE":"Lazo Chucos, Gilmer","MODULO":1,"horarios":{"SÁBADO":"11:00-14:00"},"seccion":1},{"MAESTRIA":"AGCG","CODIGO":"C3S22223","ASIGNATURA":"ESTADISTICA APLICADA A LA INVESTIGACION","HR":2,"CR":2,"Ciclo":2,"DOCENTE":"Chumpitaz Ramos, Domingo Guzmán","MODULO":2,"horarios":{"SÁBADO":"15:00-18:00"},"seccion":1},{"MAESTRIA":"AGCG","CODIGO":"C3S22224","ASIGNATURA":"SEMINARIO DE AUDITORIA DE DESEMPEÑO GUBERNAMENTAL","HR":2,"CR":3,"Ciclo":2,"DOCENTE":"Argandoña Dueñas, Marco Antonio","MODULO":1,"horarios":{"SÁBADO":"15:00-18:00"},"seccion":1},{"MAESTRIA":"AGCG","CODIGO":"C3S22233","ASIGNATURA":"TALLER DE TESIS  II","HR":4,"CR":10,"Ciclo":3,"DOCENTE":"Gomero Gonzales, Nicko Alberto","MODULO":1,"horarios":{"SÁBADO":"08:00-11:00"},"seccion":1},{"MAESTRIA":"AGCG","CODIGO":"C3S22231","ASIGNATURA":"AUDITORIAS DE TECNOLOGIAS DE LA INFORMACION","HR":2,"CR":2,"Ciclo":3,"DOCENTE":"Rojas Medina, Julio César","MODULO":1,"horarios":{"SÁBADO":"15:00-18:00"},"seccion":1},{"MAESTRIA":"AGCG","CODIGO":"C3S22232","ASIGNATURA":"TALLER DE AUDITORIA FINANCIERA GUBERNAMENTAL","HR":2,"CR":3,"Ciclo":3,"DOCENTE":"Chavez Bravo, Juan Carlos","MODULO":1,"horarios":{"SÁBADO":"11:00-14:00"},"seccion":1},{"MAESTRIA":"AGCG","CODIGO":"C3S22234","ASIGNATURA":"TALLER DE ETICA Y TRANSPARENCIA EN EL SECTOR PUBLICO","HR":2,"CR":3,"Ciclo":3,"DOCENTE":"Baca Morante, Yanette Armida","MODULO":2,"horarios":{"SÁBADO":"15:00-18:00"},"seccion":1},{"MAESTRIA":"AGCG","CODIGO":"C3S222A1","ASIGNATURA":"(ELECTIVO) PEDAGODIA UNIVERSITARIA","HR":2,"CR":2,"Ciclo":3,"DOCENTE":"Obregon Nicolas, Karim Grace","MODULO":2,"horarios":{"SÁBADO":"11:00-14:00"},"seccion":1},{"MAESTRIA":"AGCG","CODIGO":"C3P22243","ASIGNATURA":"TALLER DE TESIS III","HR":4,"CR":10,"Ciclo":4,"DOCENTE":"Ramos Costilla, Jhonny Martin","MODULO":1,"horarios":{"SÁBADO":"08:00-11:00"},"seccion":1},{"MAESTRIA":"AGCG","CODIGO":"C3P22241","ASIGNATURA":"INFORMES DE AUDITORIA GUBERNAMENTAL","HR":2,"CR":2,"Ciclo":4,"DOCENTE":"Mogrovejo Espinoza, Martín Edmundo","MODULO":1,"horarios":{"SÁBADO":"15:00-18:00"},"seccion":1},{"MAESTRIA":"AGCG","CODIGO":"C3P22242","ASIGNATURA":"AUDITORIA ESPECIALIZADA DEL SECTOR PUBLICO","HR":2,"CR":3,"Ciclo":4,"DOCENTE":"Lazo Chucos, Gilmer","MODULO":2,"horarios":{"SÁBADO":"11:00-14:00"},"seccion":1},{"MAESTRIA":"AGCG","CODIGO":"C3P22244","ASIGNATURA":"TALLER DE INVESTIGACION DE LA AUDITORIA FORENSE Y ANTICORRRUPCION","HR":2,"CR":3,"Ciclo":4,"DOCENTE":"Durand Saavedra, Demetrio Pedro","MODULO":1,"horarios":{"SÁBADO":"11:00-14:00"},"seccion":1},{"MAESTRIA":"B Y F","CODIGO":"C3S20114","ASIGNATURA":"METODOLOGIA Y DISEÑO DE LA INVESTIGACION","HR":4,"CR":9,"Ciclo":1,"DOCENTE":"Hidalgo Tupia, Manuel Alberto","MODULO":1,"horarios":{"MIÉRCOLES":"19:00-22:00"},"seccion":1},{"MAESTRIA":"B Y F","CODIGO":"C3S20115","ASIGNATURA":"METODOLOGIA Y DISEÑO DE LA INVESTIGACION","HR":4,"CR":9,"Ciclo":1,"DOCENTE":"Vasquez Gil, María Eugenia","MODULO":1,"horarios":{"MIÉRCOLES":"19:00-22:00"},"seccion":1},{"MAESTRIA":"B Y F","CODIGO":"C3S20111","ASIGNATURA":"INCLUSIÓN FINANCIERA","HR":2,"CR":2,"Ciclo":1,"DOCENTE":"Mendoza Torres, Carlos Roberto","MODULO":2,"horarios":{"LUNES":"19:00-22:00"},"seccion":1},{"MAESTRIA":"B Y F","CODIGO":"C3S20112","ASIGNATURA":"MARKETING DE PRODUCTOS Y SERVICIOS FINANCIEROS","HR":2,"CR":2,"Ciclo":1,"DOCENTE":"Ortiz Guevara, Juan Israel","MODULO":2,"horarios":{"VIERNES":"19:00-22:00"},"seccion":1},{"MAESTRIA":"B Y F","CODIGO":"C3S20113","ASIGNATURA":"TALLER DE  INVESTIGACION DEL SISTEMA FINANCIERO","HR":2,"CR":2,"Ciclo":1,"DOCENTE":"Garcia Villegas, Emilio Gabriel","MODULO":1,"horarios":{"LUNES":"19:00-22:00"},"seccion":1},{"MAESTRIA":"B Y F","CODIGO":"C3S201A3","ASIGNATURA":"Gobierno Corporativo,  Etica y Compliance","HR":2,"CR":2,"Ciclo":1,"DOCENTE":"Melgarejo Morales, Javier Ricardo","MODULO":1,"horarios":{"VIERNES":"19:00-22:00"},"seccion":1},{"MAESTRIA":"B Y F","CODIGO":"C3S20124","ASIGNATURA":"TALLER DE TESIS  I","HR":4,"CR":9,"Ciclo":2,"DOCENTE":"Obando Peralta, Ena Cecilia","MODULO":1,"horarios":{"MIÉRCOLES":"19:00-22:00"},"seccion":1},{"MAESTRIA":"B Y F","CODIGO":"C3S20121","ASIGNATURA":"ESTADISTICA APLICADA A LA INVESTIGACION","HR":2,"CR":2,"Ciclo":2,"DOCENTE":"Michue Salguedo, Efren Silverio","MODULO":1,"horarios":{"VIERNES":"19:00-22:00"},"seccion":1},{"MAESTRIA":"B Y F","CODIGO":"C3S20122","ASIGNATURA":"FINANZAS CORPORATIVAS","HR":2,"CR":3,"Ciclo":2,"DOCENTE":"Romero Cerna, José Salvador","MODULO":2,"horarios":{"VIERNES":"19:00-22:00"},"seccion":1},{"MAESTRIA":"B Y F","CODIGO":"C3S20123","ASIGNATURA":"SEMINARIO DE GESTION DE INVERSIONES","HR":2,"CR":3,"Ciclo":2,"DOCENTE":"Verástegui Corrales, Cleofé Maritza","MODULO":1,"horarios":{"LUNES":"19:00-22:00"},"seccion":1},{"MAESTRIA":"B Y F","CODIGO":"C3P20132","ASIGNATURA":"TALLER DE TESIS II","HR":4,"CR":9,"Ciclo":3,"DOCENTE":"Espinoza Valenzuela, Alberto Benjamin","MODULO":1,"horarios":{"MIÉRCOLES":"19:00-22:00"},"seccion":1},{"MAESTRIA":"B Y F","CODIGO":"C3P20132","ASIGNATURA":"TALLER DE TESIS II","HR":4,"CR":9,"Ciclo":3,"DOCENTE":"Medianero Burga, David Elpifio","MODULO":1,"horarios":{"MIÉRCOLES":"19:00-22:00"},"seccion":1},{"MAESTRIA":"B Y F","CODIGO":"C3S20131","ASIGNATURA":"GESTION DE FINANCIAMIENTO","HR":2,"CR":3,"Ciclo":3,"DOCENTE":"León Martinez, David Cirilo","MODULO":2,"horarios":{"VIERNES":"19:00-22:00"},"seccion":1},{"MAESTRIA":"B Y F","CODIGO":"C3S20133","ASIGNATURA":"TALLER DE DERECHO  BANCARIO Y FINANCIERO","HR":2,"CR":2,"Ciclo":3,"DOCENTE":"Muñoz Vara, Julio Raúl","MODULO":1,"horarios":{"VIERNES":"19:00-22:00"},"seccion":1},{"MAESTRIA":"B Y F","CODIGO":"C3S20134","ASIGNATURA":"SEMINARIO DE GESTION INTEGRAL DE RIESGOS","HR":2,"CR":3,"Ciclo":3,"DOCENTE":"Melgarejo Morales, Javier Ricardo","MODULO":2,"horarios":{"LUNES":"19:00-22:00"},"seccion":1},{"MAESTRIA":"B Y F","CODIGO":"C3P20144","ASIGNATURA":"TALLER DE TESIS III","HR":4,"CR":10,"Ciclo":4,"DOCENTE":"Pastor Carrasco, Carlos Alberto","MODULO":1,"horarios":{"MIÉRCOLES":"19:00-22:00"},"seccion":1},{"MAESTRIA":"B Y F","CODIGO":"C3P20141","ASIGNATURA":"INTELIGENCIA FINANCIERA Y VALORACION DE EMPRESAS","HR":2,"CR":3,"Ciclo":4,"DOCENTE":"Romero Cerna, José Salvador","MODULO":1,"horarios":{"LUNES":"19:00-22:00"},"seccion":1},{"MAESTRIA":"B Y F","CODIGO":"C3P20142","ASIGNATURA":"FINANZAS INTERNACIONALES","HR":2,"CR":3,"Ciclo":4,"DOCENTE":"Sánchez Cruz, David Juan","MODULO":1,"horarios":{"VIERNES":"19:00-22:00"},"seccion":1},{"MAESTRIA":"B Y F","CODIGO":"C3P20143","ASIGNATURA":"TALLER DE INVESTIGACION DE INVERSIONES Y GESTION INTEGRAL DE PROYECTOS","HR":2,"CR":2,"Ciclo":4,"DOCENTE":"Ormea Villavicencio, Javier Eduardo","MODULO":2,"horarios":{"VIERNES":"19:00-22:00"},"seccion":1}]